roj/__init__.py
roj/__main__.py
roj-0.2.4.dist-info/licenses/LICENSE
roj-0.2.4.dist-info/METADATA
roj-0.2.4.dist-info/WHEEL
roj-0.2.4.dist-info/entry_points.txt
roj-0.2.4.dist-info/top_level.txt
roj-0.2.4.dist-info/RECORD
