Metadata-Version: 2.4
Name: roj
Version: 0.2.4
Summary: roj (run on jail) runs a command (login shell by default) on a local or remote jail
Home-page: https://github.com/astralblue/roj
Author: Eugene M. Kim
Author-email: astralblue@gmail.com
Project-URL: Bug Tracker, https://github.com/astralblue/roj/issues
Classifier: Programming Language :: Python :: 3
Classifier: License :: OSI Approved :: BSD License
Classifier: Operating System :: OS Independent
Requires-Python: >=3.9
License-File: LICENSE
Dynamic: license-file
